{"meta": [{"BRAINMETA": ""}], "name": "BRAINMETA", "nid": "1", "children": [{"meta": [{"RESPONSE_INHIBITION": 0.667158153984}], "name": "RESPONSE_INHIBITION", "nid": "2", "children": [{"meta": [{"DS000009": 0.39140417247500003}], "name": "DS000009", "nid": "4", "children": [{"meta": [{"EXPLODE_4": 0.0725726465833}], "name": "EXPLODE_4", "nid": "7", "children": [{"meta": [{"task004_002_explode.nii.gz:000446.nii.gz": ""}], "name": "task004_002_explode.nii.gz:000446.nii.gz", "nid": "68", "children": []}, {"meta": [{"task001_002_explode.nii.gz:000447.nii.gz": ""}], "name": "task001_002_explode.nii.gz:000447.nii.gz", "nid": "69", "children": []}, {"meta": [{"task003_002_explode.nii.gz:000461.nii.gz": ""}], "name": "task003_002_explode.nii.gz:000461.nii.gz", "nid": "82", "children": []}, {"meta": [{"task002_002_explode.nii.gz:000465.nii.gz": ""}], "name": "task002_002_explode.nii.gz:000465.nii.gz", "nid": "83", "children": []}]}, {"meta": [{"ACCEPT_4": 0.07248668597739999}], "name": "ACCEPT_4", "nid": "8", "children": [{"meta": [{"task002_001_accept.nii.gz:000448.nii.gz": ""}], "name": "task002_001_accept.nii.gz:000448.nii.gz", "nid": "70", "children": []}, {"meta": [{"task004_001_accept.nii.gz:000450.nii.gz": ""}], "name": "task004_001_accept.nii.gz:000450.nii.gz", "nid": "71", "children": []}, {"meta": [{"task001_001_accept.nii.gz:000463.nii.gz": ""}], "name": "task001_001_accept.nii.gz:000463.nii.gz", "nid": "72", "children": []}, {"meta": [{"task001_001_accept.nii.gz:000463.nii.gz": ""}], "name": "task001_001_accept.nii.gz:000463.nii.gz", "nid": "73", "children": []}]}, {"meta": [{"ALL_4": 0.07332365235010001}], "name": "ALL_4", "nid": "9", "children": [{"meta": [{"task002_004_all.nii.gz:000449.nii.gz": ""}], "name": "task002_004_all.nii.gz:000449.nii.gz", "nid": "74", "children": []}, {"meta": [{"task001_004_all.nii.gz:000456.nii.gz": ""}], "name": "task001_004_all.nii.gz:000456.nii.gz", "nid": "75", "children": []}, {"meta": [{"task003_004_all.nii.gz:000460.nii.gz": ""}], "name": "task003_004_all.nii.gz:000460.nii.gz", "nid": "76", "children": []}, {"meta": [{"task004_004_all.nii.gz:000462.nii.gz": ""}], "name": "task004_004_all.nii.gz:000462.nii.gz", "nid": "77", "children": []}]}, {"meta": [{"ACCEPT_VS_REJECT": 0.0717331743368}], "name": "ACCEPT_VS_REJECT", "nid": "10", "children": [{"meta": [{"task003_005_accept_vs_reject.nii.gz:000451.nii.gz": ""}], "name": "task003_005_accept_vs_reject.nii.gz:000451.nii.gz", "nid": "78", "children": []}, {"meta": [{"task001_005_accept_vs_reject.nii.gz:000453.nii.gz": ""}], "name": "task001_005_accept_vs_reject.nii.gz:000453.nii.gz", "nid": "79", "children": []}, {"meta": [{"task002_005_accept_vs_reject.nii.gz:000454.nii.gz": ""}], "name": "task002_005_accept_vs_reject.nii.gz:000454.nii.gz", "nid": "80", "children": []}, {"meta": [{"task004_005_accept_vs_reject.nii.gz:000458.nii.gz": ""}], "name": "task004_005_accept_vs_reject.nii.gz:000458.nii.gz", "nid": "81", "children": []}]}, {"meta": [{"REJECT_4": 0.0719540988149}], "name": "REJECT_4", "nid": "11", "children": [{"meta": [{"task002_003_reject.nii.gz:000452.nii.gz": ""}], "name": "task002_003_reject.nii.gz:000452.nii.gz", "nid": "84", "children": []}, {"meta": [{"task004_003_reject.nii.gz:000455.nii.gz": ""}], "name": "task004_003_reject.nii.gz:000455.nii.gz", "nid": "85", "children": []}, {"meta": [{"task003_003_reject.nii.gz:000457.nii.gz": ""}], "name": "task003_003_reject.nii.gz:000457.nii.gz", "nid": "86", "children": []}, {"meta": [{"task001_003_reject.nii.gz:000459.nii.gz": ""}], "name": "task001_003_reject.nii.gz:000459.nii.gz", "nid": "87", "children": []}]}]}, {"meta": [{"DS000008": 0.26329896418800003}], "name": "DS000008", "nid": "5", "children": [{"meta": [{"GO_5": 0.033766365661200004}], "name": "GO_5", "nid": "12", "children": [{"meta": [{"task001_001_go.nii.gz:000143.nii.gz": ""}], "name": "task001_001_go.nii.gz:000143.nii.gz", "nid": "15", "children": []}, {"meta": [{"task002_001_go.nii.gz:000148.nii.gz": ""}], "name": "task002_001_go.nii.gz:000148.nii.gz", "nid": "61", "children": []}]}, {"meta": [{"SUCCESS_STOP": 0.0340712471263}], "name": "SUCCESS_STOP", "nid": "13", "children": [{"meta": [{"task002_002_successful_stop.nii.gz:000144.nii.gz": ""}], "name": "task002_002_successful_stop.nii.gz:000144.nii.gz", "nid": "55", "children": []}, {"meta": [{"task001_002_successful_stop.nii.gz:000147.nii.gz": ""}], "name": "task001_002_successful_stop.nii.gz:000147.nii.gz", "nid": "59", "children": []}]}, {"meta": [{"UNSUCCESS_MINUS_SUCCESS_STOP": 0.0347091509668}], "name": "UNSUCCESS_MINUS_SUCCESS_STOP", "nid": "14", "children": [{"meta": [{"task001_006_unsucc_minus_succ_stop.nii.gz:000145.nii.gz": ""}], "name": "task001_006_unsucc_minus_succ_stop.nii.gz:000145.nii.gz", "nid": "56", "children": []}, {"meta": [{"task002_006_unsucc_minus_succ_stop.nii.gz:000150.nii.gz": ""}], "name": "task002_006_unsucc_minus_succ_stop.nii.gz:000150.nii.gz", "nid": "60", "children": []}]}, {"meta": [{"FAILED_STOP": 0.033546518006}], "name": "FAILED_STOP", "nid": "16", "children": [{"meta": [{"task001_003_failed_stop.nii.gz:000146.nii.gz": ""}], "name": "task001_003_failed_stop.nii.gz:000146.nii.gz", "nid": "57", "children": []}, {"meta": [{"task002_003_failed_stop.nii.gz:000149.nii.gz": ""}], "name": "task002_003_failed_stop.nii.gz:000149.nii.gz", "nid": "58", "children": []}]}, {"meta": [{"SUCCESS_MINUS_GO": 0.0340032207674}], "name": "SUCCESS_MINUS_GO", "nid": "17", "children": [{"meta": [{"task001_007_succstop_minus_go.nii.gz:000151.nii.gz": ""}], "name": "task001_007_succstop_minus_go.nii.gz:000151.nii.gz", "nid": "62", "children": []}, {"meta": [{"task002_007_succstop_minus_go.nii.gz:000155.nii.gz": ""}], "name": "task002_007_succstop_minus_go.nii.gz:000155.nii.gz", "nid": "63", "children": []}]}, {"meta": [{"ALL_5": 0.0337617831204}], "name": "ALL_5", "nid": "18", "children": [{"meta": [{"task001_005_all.nii.gz:000152.nii.gz": ""}], "name": "task001_005_all.nii.gz:000152.nii.gz", "nid": "64", "children": []}, {"meta": [{"task002_005_all.nii.gz:000154.nii.gz": ""}], "name": "task002_005_all.nii.gz:000154.nii.gz", "nid": "65", "children": []}]}, {"meta": [{"JUNK": 0.034224644756099994}], "name": "JUNK", "nid": "19", "children": [{"meta": [{"task002_004_junk.nii.gz:000142.nii.gz": ""}], "name": "task002_004_junk.nii.gz:000142.nii.gz", "nid": "66", "children": []}, {"meta": [{"task001_004_junk.nii.gz:000153.nii.gz": ""}], "name": "task001_004_junk.nii.gz:000153.nii.gz", "nid": "67", "children": []}]}]}]}, {"meta": [{"RISK_SEEKING": 0.329878227663}], "name": "RISK_SEEKING", "nid": "3", "children": [{"meta": [{"DS000001": 0.329878227663}], "name": "DS000001", "nid": "6", "children": [{"meta": [{"PUMPS_FIXED_RT": ""}], "name": "PUMPS_FIXED_RT", "nid": "20", "children": []}, {"meta": [{"CASH_FIXED_REAL_RT": 0.015500629411500001}], "name": "CASH_FIXED_REAL_RT", "nid": "21", "children": [{"meta": [{"task001_006_cash_fixed_real_RT.nii.gz:000117.nii.gz": ""}], "name": "task001_006_cash_fixed_real_RT.nii.gz:000117.nii.gz", "nid": "42", "children": []}]}, {"meta": [{"CASH_FIXED": 0.015541606668899999}], "name": "CASH_FIXED", "nid": "22", "children": [{"meta": [{"task001_004_cash_fixed.nii.gz:000118.nii.gz": ""}], "name": "task001_004_cash_fixed.nii.gz:000118.nii.gz", "nid": "43", "children": []}]}, {"meta": [{"EXPLODE_6": 0.0152240736261}], "name": "EXPLODE_6", "nid": "23", "children": [{"meta": [{"task001_007_explode_fixed.nii.gz:000119.nii.gz": ""}], "name": "task001_007_explode_fixed.nii.gz:000119.nii.gz", "nid": "44", "children": []}]}, {"meta": [{"PUMPS_FIXED": 0.014921882951700001}], "name": "PUMPS_FIXED", "nid": "24", "children": [{"meta": [{"task001_001_pumps_fixed.nii.gz:000120.nii.gz": ""}], "name": "task001_001_pumps_fixed.nii.gz:000120.nii.gz", "nid": "45", "children": []}]}, {"meta": [{"CONTROL_PUMPS_FIXED_RT": 0.0154177636283}], "name": "CONTROL_PUMPS_FIXED_RT", "nid": "25", "children": [{"meta": [{"task001_011_control_pumps_fixed_real_RT.nii.gz:000121.nii.gz": ""}], "name": "task001_011_control_pumps_fixed_real_RT.nii.gz:000121.nii.gz", "nid": "46", "children": []}]}, {"meta": [{"PUMPS_DEMEAN": 0.0152627103296}], "name": "PUMPS_DEMEAN", "nid": "26", "children": [{"meta": [{"task001_002_pumps_demean.nii.gz:000122.nii.gz": ""}], "name": "task001_002_pumps_demean.nii.gz:000122.nii.gz", "nid": "47", "children": []}]}, {"meta": [{"CONTROL_PUMPS_FIXED": 0.0149725715365}], "name": "CONTROL_PUMPS_FIXED", "nid": "27", "children": [{"meta": [{"task001_009_control_pumps_fixed.nii.gz:000123.nii.gz": ""}], "name": "task001_009_control_pumps_fixed.nii.gz:000123.nii.gz", "nid": "48", "children": []}]}, {"meta": [{"PUMPS_REAL_RT_MINUS_CTRL_REAL_RT": 0.0154523045542}], "name": "PUMPS_REAL_RT_MINUS_CTRL_REAL_RT", "nid": "28", "children": [{"meta": [{"task001_015_pumps_realRT_minus_ctrl_realRT.nii.gz:000127.nii.gz": ""}], "name": "task001_015_pumps_realRT_minus_ctrl_realRT.nii.gz:000127.nii.gz", "nid": "52", "children": []}]}, {"meta": [{"PUMPS_DEMEAN_MINUS_CTRL_DEMEAN": 0.01527614676}], "name": "PUMPS_DEMEAN_MINUS_CTRL_DEMEAN", "nid": "29", "children": [{"meta": [{"task001_017_pumps_demean_minus_ctrl_demean.nii.gz:000124.nii.gz": ""}], "name": "task001_017_pumps_demean_minus_ctrl_demean.nii.gz:000124.nii.gz", "nid": "49", "children": []}]}, {"meta": [{"CASH_DEMEAN": 0.0154635784828}], "name": "CASH_DEMEAN", "nid": "30", "children": [{"meta": [{"task001_005_cash_demean.nii.gz:000125.nii.gz": ""}], "name": "task001_005_cash_demean.nii.gz:000125.nii.gz", "nid": "50", "children": []}]}, {"meta": [{"CTRL_FIXED_MINUS_PUMPS_FIXED": 0.014561367161700001}], "name": "CTRL_FIXED_MINUS_PUMPS_FIXED", "nid": "31", "children": [{"meta": [{"task001_013_ctrl_fixed_minus_pumps_fixed.nii.gz:000126.nii.gz": ""}], "name": "task001_013_ctrl_fixed_minus_pumps_fixed.nii.gz:000126.nii.gz", "nid": "51", "children": []}]}, {"meta": [{"ALL_6": 0.0154413510591}], "name": "ALL_6", "nid": "33", "children": [{"meta": [{"task001_012_all.nii.gz:000129.nii.gz": ""}], "name": "task001_012_all.nii.gz:000129.nii.gz", "nid": "53", "children": []}]}, {"meta": [{"CTRL_PUMPS_DEMEAN": 0.0151309294995}], "name": "CTRL_PUMPS_DEMEAN", "nid": "36", "children": [{"meta": [{"task001_010_control_pumps_demean.nii.gz:000130.nii.gz": ""}], "name": "task001_010_control_pumps_demean.nii.gz:000130.nii.gz", "nid": "32", "children": []}]}, {"meta": [{"CTRL_REAL_RT_MINUS_PUMPS_REAL_RT": 0.015413363812799999}], "name": "CTRL_REAL_RT_MINUS_PUMPS_REAL_RT", "nid": "37", "children": [{"meta": [{"task001_016_ctrl_realRT_minus_pumps_realRT.nii.gz:000131.nii.gz": ""}], "name": "task001_016_ctrl_realRT_minus_pumps_realRT.nii.gz:000131.nii.gz", "nid": "34", "children": []}]}, {"meta": [{"PUMPS_FIXED_MINUS_CTRL_FIXED": 0.0150031875382}], "name": "PUMPS_FIXED_MINUS_CTRL_FIXED", "nid": "38", "children": [{"meta": [{"task001_018_pumps_fixed_minus_ctrl_fixed.nii.gz:000132.nii.gz": ""}], "name": "task001_018_pumps_fixed_minus_ctrl_fixed.nii.gz:000132.nii.gz", "nid": "35", "children": []}]}, {"meta": [{"CTRL_DEMEAN_MINUS_PUMPS_DEMEAN": 0.0149275476251}], "name": "CTRL_DEMEAN_MINUS_PUMPS_DEMEAN", "nid": "39", "children": [{"meta": [{"task001_014_ctrl_demean_minus_pumps_demean.nii.gz:000115.nii.gz": ""}], "name": "task001_014_ctrl_demean_minus_pumps_demean.nii.gz:000115.nii.gz", "nid": "54", "children": []}]}, {"meta": [{"PUMPS_FIXED_REAL_RT": 0.015406438368500001}], "name": "PUMPS_FIXED_REAL_RT", "nid": "40", "children": [{"meta": [{"task001_003_pumps_fixed_real_RT.nii.gz:000116.nii.gz": ""}], "name": "task001_003_pumps_fixed_real_RT.nii.gz:000116.nii.gz", "nid": "41", "children": []}]}]}]}]}